templatify/__init__.py
templatify-0.0.4.dist-info/METADATA
templatify-0.0.4.dist-info/WHEEL
templatify-0.0.4.dist-info/licenses/LICENSE
templatify-0.0.4.dist-info/RECORD
