Metadata-Version: 2.1
Name: templatify
Version: 0.0.4
License-File: LICENSE
Requires-Dist: jinja2
